dailyDecisionPackage/__init__.py
dailyDecisionPackage/dailyDecision.py
dailydecisionpackage-0.0.2.dist-info/licenses/LICENSE
dailydecisionpackage-0.0.2.dist-info/METADATA
dailydecisionpackage-0.0.2.dist-info/WHEEL
dailydecisionpackage-0.0.2.dist-info/top_level.txt
dailydecisionpackage-0.0.2.dist-info/RECORD
