Metadata-Version: 2.4
Name: dailyDecisionPackage
Version: 0.0.2
Summary: A lighthearted Python package that helps you make everyday decisions.
Author: Jubilee Tang, Maria Lee, Reece Huey, Anshu Aramandla, Natalie Han
License-Expression: GPL-3.0-or-later
Project-URL: Homepage, https://github.com/swe-students-fall2025/3-python-package-team_aurora
Project-URL: Repository, https://github.com/swe-students-fall2025/3-python-package-team_aurora.git
Keywords: python,package,daily,decision,helper,color,food
Classifier: Programming Language :: Python :: 3
Classifier: Intended Audience :: Education
Classifier: Operating System :: OS Independent
Requires-Python: >=3.9
License-File: LICENSE
Provides-Extra: dev
Requires-Dist: pytest; extra == "dev"
Requires-Dist: build; extra == "dev"
Requires-Dist: twine; extra == "dev"
Dynamic: license-file
